scrapify_ig/__init__.py
scrapify_ig/client.py
scrapify_ig/exceptions.py
scrapify_ig/mixins/__init__.py
scrapify_ig/mixins/media_post.py
scrapify_ig/mixins/search.py
scrapify_ig/mixins/user.py
scrapify_ig/request.py
scrapify_ig/types.py
scrapify_ig-1.7.1.dist-info/LICENSE
scrapify_ig-1.7.1.dist-info/METADATA
scrapify_ig-1.7.1.dist-info/WHEEL
scrapify_ig-1.7.1.dist-info/RECORD
