Metadata-Version: 2.1
Name: scrapify-ig
Version: 1.7.1
Summary: Python Instagram API SDK
Home-page: https://gitlab.com/oleksii.stulen.public/scrapify-ig
License: MIT
Author: Oleksii Stulen
Author-email: oleksii.stulen.workspace@gmail.com
Requires-Python: >=3.9,<4.0
Classifier: License :: OSI Approved :: MIT License
Classifier: Programming Language :: Python :: 3
Classifier: Programming Language :: Python :: 3.9
Classifier: Programming Language :: Python :: 3.10
Classifier: Programming Language :: Python :: 3.11
Requires-Dist: pydantic (>=1.10.7,<2.0.0)
Requires-Dist: requests (>=2.31.0,<3.0.0)
Project-URL: Repository, https://gitlab.com/oleksii.stulen.public/scrapify-ig
